[
  {
    "salida": "2024-08-27",
    "llegada": "2024-09-25",
    "origen": "BAS",
    "destino": "BAS",
    "transporteId": "",
    "personalId": "persona2",
    "maquinariaId": "maquinaria1",
    "cerrada": false,
    "unidad": "kg",
    "codigo": 1
  },
  {
    "salida": "2024-07-15",
    "llegada": "2024-07-20",
    "origen": "MEX",
    "destino": "USA",
    "transporteId": "",
    "personalId": "persona3",
    "maquinariaId": "maquinaria4",
    "cerrada": true,
    "unidad": "kg",
    "codigo": 2
  },
  {
    "salida": "2024-09-01",
    "llegada": "2024-09-05",
    "origen": "BRA",
    "destino": "ARG",
    "transporteId": "transporte1",
    "personalId": "",
    "maquinariaId": "",
    "cerrada": false,
    "unidad": "ton",
    "codigo": 3
  },
  {
    "salida": "2024-01-01",
    "llegada": "2024-01-02",
    "origen": "PER",
    "destino": "CHI",
    "transporteId": "",
    "personalId": "persona4",
    "maquinariaId": "maquinaria5",
    "cerrada": false,
    "unidad": "kg",
    "codigo": 4
  },
  {
    "salida": "2024-02-01",
    "llegada": "2024-02-02",
    "origen": "USA",
    "destino": "CAN",
    "transporteId": "",
    "personalId": "persona5",
    "maquinariaId": "maquinaria6",
    "cerrada": false,
    "unidad": "ton",
    "codigo": 5
  },
  {
    "salida": "2024-03-01",
    "llegada": "2024-03-02",
    "origen": "ARG",
    "destino": "BRA",
    "transporteId": "transporte4",
    "personalId": "",
    "maquinariaId": "",
    "cerrada": false,
    "unidad": "kg",
    "codigo": 6
  },
  {
    "salida": "2024-04-01",
    "llegada": "2024-04-02",
    "origen": "CHI",
    "destino": "PER",
    "transporteId": "",
    "personalId": "persona7",
    "maquinariaId": "maquinaria8",
    "cerrada": false,
    "unidad": "ton",
    "codigo": 7
  }
]
  