[
    {
        "Remitosid": 1,
        "nombre": "Merrill Inchley"
    },
    {
        "Remitosid": 2,
        "nombre": "Arline Kersley"
    },
    {
        "Remitosid": 3,
        "nombre": "Smith Haxley"
    },
    {
        "Remitosid": 4,
        "nombre": "Ryann Briar"
    },
    {
        "Remitosid": 5,
        "nombre": "Renell Morrell"
    },
    {
        "Remitosid": 6,
        "nombre": "Zara Abys"
    },
    {
        "Remitosid": 7,
        "nombre": "Rosie Magowan"
    },
    {
        "Remitosid": 8,
        "nombre": "Piotr Caccavella"
    },
    {
        "Remitosid": 9,
        "nombre": "Lorin Pude"
    },
    {
        "Remitosid": 10,
        "nombre": "Victoir Annear"
    }
]
